setup.cfg
setup.py
simplefsabstraction/__init__.py
simplefsabstraction/interface.py
simplefsabstraction/local.py
simplefsabstraction/s3.py
simplefsabstraction.egg-info/PKG-INFO
simplefsabstraction.egg-info/SOURCES.txt
simplefsabstraction.egg-info/dependency_links.txt
simplefsabstraction.egg-info/requires.txt
simplefsabstraction.egg-info/top_level.txt