Metadata-Version: 1.1
Name: simplefsabstraction
Version: 1.3.1
Summary: A (very) simple FS/S3 abstraction
Home-page: https://github.com/brendan-rius/simplefsabstraction/
Author: Brendan Rius
Author-email: ping@brendan-rius.com
License: UNKNOWN
Download-URL: https://github.com/brendan-rius/simplefsabstraction/tarball/1.3.1
Keywords: fs,s3
Platform: UNKNOWN
